sagellm_control/__init__.py
sagellm_control/__init__.pyc
sagellm_control/engine_client.pyc
sagellm_control/lifecycle.pyc
sagellm_control/local_engine_client.pyc
sagellm_control/manager.pyc
sagellm_control/py.typed
sagellm_control/router.pyc
sagellm_control/scaling.pyc
sagellm_control/types.pyc
sagellm_control/__pycache__/__init__.cpython-311.pyc
sagellm_control/__pycache__/engine_client.cpython-311.pyc
sagellm_control/__pycache__/lifecycle.cpython-311.pyc
sagellm_control/__pycache__/local_engine_client.cpython-311.pyc
sagellm_control/__pycache__/manager.cpython-311.pyc
sagellm_control/__pycache__/mock.cpython-311.pyc
sagellm_control/__pycache__/router.cpython-311.pyc
sagellm_control/__pycache__/scaling.cpython-311.pyc
sagellm_control/__pycache__/types.cpython-311.pyc
sagellm_control/policies/__init__.py
sagellm_control/policies/__init__.pyc
sagellm_control/policies/adaptive.pyc
sagellm_control/policies/base.pyc
sagellm_control/policies/fifo.pyc
sagellm_control/policies/priority.pyc
sagellm_control/policies/slo_aware.pyc
sagellm_control/policies/__pycache__/__init__.cpython-311.pyc
sagellm_control/policies/__pycache__/adaptive.cpython-311.pyc
sagellm_control/policies/__pycache__/base.cpython-311.pyc
sagellm_control/policies/__pycache__/fifo.cpython-311.pyc
sagellm_control/policies/__pycache__/priority.cpython-311.pyc
sagellm_control/policies/__pycache__/slo_aware.cpython-311.pyc
isagellm_control_plane-0.4.0.12.dist-info/METADATA
isagellm_control_plane-0.4.0.12.dist-info/WHEEL
isagellm_control_plane-0.4.0.12.dist-info/top_level.txt
isagellm_control_plane-0.4.0.12.dist-info/RECORD
