Metadata-Version: 2.4
Name: isagellm-control-plane
Version: 0.4.0.12
Summary: sageLLM Control Plane - Intelligent request routing, scheduling, and engine lifecycle management
Author: IntelliStream Team
License: Proprietary - IntelliStream
Project-URL: Homepage, https://github.com/IntelliStream/sagellm-control-plane
Project-URL: Repository, https://github.com/IntelliStream/sagellm-control-plane
Keywords: llm,inference,control-plane,scheduling,routing,autoscaling
Classifier: Development Status :: 3 - Alpha
Classifier: Programming Language :: Python :: 3
Classifier: Programming Language :: Python :: 3.10
Classifier: Programming Language :: Python :: 3.11
Classifier: Programming Language :: Python :: 3.12
Classifier: Topic :: Scientific/Engineering :: Artificial Intelligence
Requires-Python: ==3.11.*
Requires-Dist: isagellm-protocol<0.5.0,>=0.4.0.0
Requires-Dist: pydantic>=2.0.0
Requires-Dist: httpx>=0.24.0
Provides-Extra: dev
Requires-Dist: pytest>=7.0.0; extra == "dev"
Requires-Dist: pytest-asyncio>=0.21.0; extra == "dev"
Requires-Dist: pytest-cov>=4.0.0; extra == "dev"
Requires-Dist: ruff>=0.8.0; extra == "dev"
Requires-Dist: mypy>=1.0.0; extra == "dev"
Requires-Dist: isage-pypi-publisher>=0.2.0; extra == "dev"
